[
    {
        "icon": "devicon:html5",
        "data-tooltip-content": "HTML5"
    },
    {
        "icon": "devicon:css3",
        "data-tooltip-content": "CSS3"
    },
    {
        "icon": "devicon:javascript",
        "data-tooltip-content": "JavaScript"
    },
    {
        "icon": "devicon:typescript",
        "data-tooltip-content": "TypeScript"
    },
    {
        "icon": "devicon:tailwindcss",
        "data-tooltip-content": "Tailwind CSS"
    },
    {
        "icon": "vscode-icons:file-type-reactjs",
        "data-tooltip-content": "ReactJS"
    },
    {
        "icon": "vscode-icons:file-type-vue",
        "data-tooltip-content": "VueJS"
    },
    {
        "icon": "devicon:vuetify",
        "data-tooltip-content": "Vuetify 3"
    },
    {
        "icon": "devicon:nodejs-wordmark",
        "data-tooltip-content": "NodeJS"
    },
    {
        "icon": "skill-icons:expressjs-light",
        "data-tooltip-content": "ExpressJS"
    },
    {
        "icon": "devicon:git",
        "data-tooltip-content": "Git"
    },
    {
        "icon": "devicon:github",
        "data-tooltip-content": "GitHub"
    },
    {
        "icon": "devicon:vercel-wordmark",
        "data-tooltip-content": "Vercel"
    },
    {
        "icon": "devicon:vscode",
        "data-tooltip-content": "Visual Studio Code"
    },
    {
        "icon": "devicon:firebase",
        "data-tooltip-content": "Firebase"
    },
    {
        "icon": "logos:mysql",
        "data-tooltip-content": "MySQL"
    },
    {
        "icon": "devicon:mongodb-wordmark",
        "data-tooltip-content": "MongoDB"
    },
    {
        "icon": "logos:nvm",
        "data-tooltip-content": "NVM"
    },
    {
        "icon": "vscode-icons:file-type-vite",
        "data-tooltip-content": "ViteJS"
    },
    {
        "icon": "devicon:python",
        "data-tooltip-content": "Python"
    },
    {
        "icon": "devicon:cplusplus",
        "data-tooltip-content": "C++"
    },
    {
        "icon": "logos:java",
        "data-tooltip-content": "Java"
    },
    {
        "icon": "vscode-icons:file-type-php",
        "data-tooltip-content": "PHP"
    },
    {
        "icon": "devicon:photoshop",
        "data-tooltip-content": "Photoshop"
    },
    {
        "icon": "skill-icons:illustrator",
        "data-tooltip-content": "Illustrator"
    },
    {
        "icon": "skill-icons:premiere",
        "data-tooltip-content": "Premiere Pro"
    },
    {
        "icon": "skill-icons:aftereffects",
        "data-tooltip-content": "After Effects"
    },
    {
        "icon": "devicon:xd",
        "data-tooltip-content": "Adobe XD"
    }
]
